miniwdl_slurm/__init__.py
miniwdl_slurm/scripts/exec_script.sh
miniwdl_slurm-0.4.0.dist-info/licenses/LICENSE
miniwdl_slurm-0.4.0.dist-info/METADATA
miniwdl_slurm-0.4.0.dist-info/WHEEL
miniwdl_slurm-0.4.0.dist-info/entry_points.txt
miniwdl_slurm-0.4.0.dist-info/top_level.txt
miniwdl_slurm-0.4.0.dist-info/RECORD
