Metadata-Version: 2.4
Name: miniwdl-slurm
Version: 0.4.0
Summary: miniwdl slurm backend using singularity
Author-email: Leiden University Medical Center <sasc@lumc.nl>
License-Expression: MIT
Project-URL: Homepage, https://github.com/miniwdl-ext/miniwdl-slurm
Keywords: WDL,miniwdl,slurm,backend,singularity
Classifier: Development Status :: 4 - Beta
Classifier: Programming Language :: Python :: 3 :: Only
Classifier: Topic :: System :: Distributed Computing
Requires-Python: >=3.9
License-File: LICENSE
Requires-Dist: miniwdl>=1.7.0
Dynamic: license-file
